onionbalance/__init__.py
onionbalance/manager.py
onionbalance/manpages.py
onionbalance/common/__init__.py
onionbalance/common/argparser.py
onionbalance/common/descriptor.py
onionbalance/common/instance.py
onionbalance/common/intro_point_set.py
onionbalance/common/log.py
onionbalance/common/scheduler.py
onionbalance/common/signalhandler.py
onionbalance/common/status.py
onionbalance/common/util.py
onionbalance/config_generator/__init__.py
onionbalance/config_generator/config_generator.py
onionbalance/config_generator/data/config.example.yaml
onionbalance/config_generator/data/torrc-instance-v3
onionbalance/config_generator/data/torrc-server
onionbalance/hs_v3/__init__.py
onionbalance/hs_v3/consensus.py
onionbalance/hs_v3/descriptor.py
onionbalance/hs_v3/hashring.py
onionbalance/hs_v3/instance.py
onionbalance/hs_v3/manager.py
onionbalance/hs_v3/onionbalance.py
onionbalance/hs_v3/params.py
onionbalance/hs_v3/service.py
onionbalance/hs_v3/status.py
onionbalance/hs_v3/stem_controller.py
onionbalance/hs_v3/tor_ed25519.py
onionbalance/hs_v3/tor_node.py
onionbalance/hs_v3/ext/__init__.py
onionbalance/hs_v3/ext/ed25519_exts_ref.py
onionbalance/hs_v3/ext/slow_ed25519.py
onionbalance-0.2.4.dist-info/licenses/COPYING
onionbalance-0.2.4.dist-info/METADATA
onionbalance-0.2.4.dist-info/WHEEL
onionbalance-0.2.4.dist-info/entry_points.txt
onionbalance-0.2.4.dist-info/top_level.txt
onionbalance-0.2.4.dist-info/RECORD
