Metadata-Version: 2.4
Name: Onionbalance
Version: 0.2.4
Summary: Onionbalance provides load-balancing and redundancy for Tor hidden services by distributing requests to multiple backend Tor instances.
Home-page: https://gitlab.torproject.org/tpo/onion-services/onionbalance/
Author: Silvio Rhatto, George Kadianakis, Donncha O'Cearbhaill
Author-email: rhatto@torproject.org
License: GPL
Keywords: tor
Classifier: Development Status :: 3 - Alpha
Classifier: License :: OSI Approved :: GNU General Public License (GPL)
Classifier: Programming Language :: Python :: 2
Classifier: Programming Language :: Python :: 2.7
Classifier: Programming Language :: Python :: 3
Classifier: Programming Language :: Python :: 3.4
Requires-Python: >=3.6
License-File: COPYING
Requires-Dist: setuptools
Requires-Dist: stem>=1.8
Requires-Dist: PyYAML>=4.2b1
Requires-Dist: pycryptodomex
Requires-Dist: setproctitle
Requires-Dist: cryptography>=2.5
Dynamic: author
Dynamic: author-email
Dynamic: classifier
Dynamic: description
Dynamic: description-content-type
Dynamic: home-page
Dynamic: keywords
Dynamic: license
Dynamic: license-file
Dynamic: requires-dist
Dynamic: requires-python
Dynamic: summary
